lazy_pandas/__init__.py
lazy_pandas/exceptions.py
lazy_pandas/general.py
lazy_pandas/utils.py
lazy_pandas/column/__init__.py
lazy_pandas/column/lazy_column.py
lazy_pandas/column/lazy_datetime_column.py
lazy_pandas/column/lazy_string_column.py
lazy_pandas/frame/__init__.py
lazy_pandas/frame/lazy_frame.py
lazy_pandas/frame/lazy_groupped_frame.py
lazy_pandas-0.1.0.dist-info/METADATA
lazy_pandas-0.1.0.dist-info/WHEEL
lazy_pandas-0.1.0.dist-info/licenses/LICENSE
lazy_pandas-0.1.0.dist-info/RECORD
