Metadata-Version: 2.4
Name: lazy_pandas
Version: 0.1.0
Summary: The power of duckdb with the ease of pandas
License-File: LICENSE
Requires-Python: >=3.10
Requires-Dist: duckdb
